nucleus_driver/__init__.py
nucleus_driver/_assert.py
nucleus_driver/_commands.py
nucleus_driver/_connection.py
nucleus_driver/_download.py
nucleus_driver/_flash.py
nucleus_driver/_logger.py
nucleus_driver/_messages.py
nucleus_driver/_parser.py
nucleus_driver/_syslog.py
nucleus_driver/_version.py
nucleus_driver/app.py
nucleus_driver/nucleus_driver.py
nucleus_driver-1.7.2.dist-info/licenses/LICENSE.txt
nucleus_driver-1.7.2.dist-info/METADATA
nucleus_driver-1.7.2.dist-info/WHEEL
nucleus_driver-1.7.2.dist-info/entry_points.txt
nucleus_driver-1.7.2.dist-info/top_level.txt
nucleus_driver-1.7.2.dist-info/RECORD
