Metadata-Version: 2.4
Name: nucleus_driver
Version: 1.7.2
Summary: driver for the Nortek Nucleus
Home-page: https://github.com/nortekgroup/nucleus_driver
Author: Martin Bergene Johansen
Author-email: martin.johansen@nortekgroup.com
Classifier: Programming Language :: Python :: 3.7
Classifier: License :: OSI Approved :: MIT License
Classifier: Operating System :: OS Independent
Requires-Python: >=3.7
License-File: LICENSE.txt
Requires-Dist: pyserial>=3.5
Requires-Dist: cmd2>=2.4.2
Dynamic: license-file
